Metadata-Version: 2.1
Name: vk-api-lite
Version: 0.0.4
Summary: Небольшая библиотека для работы с VK API через access_token (wall.post, wall.get, photos.save)
Home-page: https://github.com/vkapilitelib/vk_api_lite
Author: Chesnokov MA
Author-email: chesnkov.malex@gmail.com
License: UNKNOWN
Platform: UNKNOWN
Classifier: Programming Language :: Python :: 3.7
Classifier: License :: OSI Approved :: GNU General Public License v3 (GPLv3)
